demo/__init__.py
demo/main.py
demo/node/DemoNode1.py
demo/node/DemoNode2.py
demo/node/__init__.py
mpflow/__init__.py
mpflow/bus.py
mpflow/context.py
mpflow/node.py
mpflow-0.0.5.dist-info/METADATA
mpflow-0.0.5.dist-info/WHEEL
mpflow-0.0.5.dist-info/top_level.txt
mpflow-0.0.5.dist-info/RECORD
