Metadata-Version: 2.1
Name: mpflow
Version: 0.0.5
Summary: A multiprocess real-time data process flow
Home-page: https://github.com/MaLangTeam/mpflow
Author: DannyLee1991
Author-email: 747554505@qq.com
License: GPLv3
Platform: UNKNOWN
Classifier: Programming Language :: Python :: 3
Classifier: License :: OSI Approved :: GNU General Public License v3 (GPLv3)
Classifier: Operating System :: OS Independent
Requires-Python: >=3.6.9
Requires-Dist: loguru (>=0.6.0)
Requires-Dist: pyyaml (>=6.0)
Requires-Dist: psutil (>=5.9.0)
